[
  {
    "name": "Cachorro",
    "url": "https://raw.githubusercontent.com/TioMarkZ/apis/main/animais/cachorro.jpg",
    "what": "Animais"
  },
  {
    "name": "Cachorro caramelo",
    "url": "https://raw.githubusercontent.com/TioMarkZ/apis/main/animais/cachorro_caramelo.jpg",
    "what": "Animais"
  },
  {
    "name": "Caititu",
    "url": "https://raw.githubusercontent.com/TioMarkZ/apis/main/animais/Caititu.jpg",
    "what": "Animais"
  },
  {
    "name": "Gato",
    "url": "https://raw.githubusercontent.com/TioMarkZ/apis/main/animais/gato.jpg",
    "what": "Animais"
  },
  {
    "name": "Elefante",
    "url": "https://raw.githubusercontent.com/TioMarkZ/apis/main/animais/elefante.jpg",
    "what": "Animais"
  },
  {
    "name": "Leão",
    "url": "https://raw.githubusercontent.com/TioMarkZ/apis/main/animais/leao.jpg",
    "what": "Animais"
  },
  {
    "name": "Leoa",
    "url": "https://raw.githubusercontent.com/TioMarkZ/apis/main/animais/leoa.jpg",
    "what": "Animais"
  },
  {
    "name": "Tigre",
    "url": "https://raw.githubusercontent.com/TioMarkZ/apis/main/animais/tigre_bengala.jpg",
    "what": "Animais"
  },
  {
    "name": "Urso",
    "url": "https://raw.githubusercontent.com/TioMarkZ/apis/main/animais/urso.jpg",
    "what": "Animais"
  },
  {
    "name": "Girafa",
    "url": "https://raw.githubusercontent.com/TioMarkZ/apis/main/animais/girafa.jpg",
    "what": "Animais"
  },
  {
    "name": "Zebra",
    "url": "https://raw.githubusercontent.com/TioMarkZ/apis/main/animais/zebra.jpg",
    "what": "Animais"
  },
  {
    "name": "Pinguim",
    "url": "https://raw.githubusercontent.com/TioMarkZ/apis/main/animais/pinguim.jpg",
    "what": "Animais"
  },
  {
    "name": "Leopardo",
    "url": "https://raw.githubusercontent.com/TioMarkZ/apis/main/animais/leopardo.jpg",
    "what": "Animais"
  },
  {
    "name": "Hipopótamo",
    "url": "https://raw.githubusercontent.com/TioMarkZ/apis/main/animais/hipopotamo.jpg",
    "what": "Animais"
  },
  {
    "name": "Cavalo",
    "url": "https://raw.githubusercontent.com/TioMarkZ/apis/main/animais/cavalo.jpg",
    "what": "Animais"
  },
  {
    "name": "Cavalo marinho",
    "url": "https://raw.githubusercontent.com/TioMarkZ/apis/main/animais/cavalo_marinho.jpg",
    "what": "Animais"
  },
  {
    "name": "Macaco",
    "url": "https://raw.githubusercontent.com/TioMarkZ/apis/main/animais/macaco.jpg",
    "what": "Animais"
  },
  {
    "name": "Gorila",
    "url": "https://raw.githubusercontent.com/TioMarkZ/apis/main/animais/gorila.jpg",
    "what": "Animais"
  },
  {
    "name": "Gorila das montanhas",
    "url": "https://raw.githubusercontent.com/TioMarkZ/apis/main/animais/gorila_das_montanhas.jpg",
    "what": "Animais"
  },
  {
    "name": "Pato",
    "url": "https://raw.githubusercontent.com/TioMarkZ/apis/main/animais/pato.jpg",
    "what": "Animais"
  },
  {
    "name": "Baleia",
    "url": "https://raw.githubusercontent.com/TioMarkZ/apis/main/animais/baleia.jpg",
    "what": "Animais"
  },
  {
    "name": "Baleia jubarte",
    "url": "https://raw.githubusercontent.com/TioMarkZ/apis/main/animais/baleia_jubarte.jpg",
    "what": "Animais"
  },
  {
    "name": "Baleia-franca-do-atlântico-norte",
    "url": "https://raw.githubusercontent.com/TioMarkZ/apis/main/animais/baleia_franca_do_atlantico_norte.jpg",
    "what": "Animais"
  },
  {
    "name": "Tubarão",
    "url": "https://raw.githubusercontent.com/TioMarkZ/apis/main/animais/tubarao.jpg",
    "what": "Animais"
  },
  {
    "name": "Tubarão-branco",
    "url": "https://raw.githubusercontent.com/TioMarkZ/apis/main/animais/tubarao_branco.jpg",
    "what": "Animais"
  },
  {
    "name": "Tubarão-martelo",
    "url": "https://raw.githubusercontent.com/TioMarkZ/apis/main/animais/tubarao_martelo.jpg",
    "what": "Animais"
  },
  {
    "name": "Tubarão-baleia",
    "url": "https://raw.githubusercontent.com/TioMarkZ/apis/main/animais/tubarao_baleia.jpg",
    "what": "Animais"
  },
  {
    "name": "Coruja",
    "url": "https://raw.githubusercontent.com/TioMarkZ/apis/main/animais/coruja.jpg",
    "what": "Animais"
  },
  {
    "name": "Coruja branca",
    "url": "https://raw.githubusercontent.com/TioMarkZ/apis/main/animais/coruja_branca.jpg",
    "what": "Animais"
  },
  {
    "name": "Camelo",
    "url": "https://raw.githubusercontent.com/TioMarkZ/apis/main/animais/camelo.jpg",
    "what": "Animais"
  },
  {
    "name": "Dromedário",
    "url": "https://raw.githubusercontent.com/TioMarkZ/apis/main/animais/dromedario.jpg",
    "what": "Animais"
  },
  {
    "name": "Crocodilo",
    "url": "https://raw.githubusercontent.com/TioMarkZ/apis/main/animais/crocodilo.jpg",
    "what": "Animais"
  },
  {
    "name": "Crocodilo-do-nilo",
    "url": "https://raw.githubusercontent.com/TioMarkZ/apis/main/animais/crocodilo_do_nilo.jpg",
    "what": "Animais"
  },
  {
    "name": "Jacaré",
    "url": "https://raw.githubusercontent.com/TioMarkZ/apis/main/animais/jacare.jpg",
    "what": "Animais"
  },
  {
    "name": "Jacaré-do-pantanal",
    "url": "https://raw.githubusercontent.com/TioMarkZ/apis/main/animais/jacare_do_pantanal.jpg",
    "what": "Animais"
  },
  {
    "name": "jacaré-do-papo-amarelo",
    "url": "https://raw.githubusercontent.com/TioMarkZ/apis/main/animais/jacare_do_papo_amarelo.jpg",
    "what": "Animais"
  },
  {
    "name": "Lobo",
    "url": "https://raw.githubusercontent.com/TioMarkZ/apis/main/animais/lobo.jpg",
    "what": "Animais"
  },
  {
    "name": "Lobo-cinzento",
    "url": "https://raw.githubusercontent.com/TioMarkZ/apis/main/animais/lobo_cinzento.jpg",
    "what": "Animais"
  },
  {
    "name": "Cobra Jararaca",
    "url": "https://raw.githubusercontent.com/TioMarkZ/apis/main/animais/jararaca.jpg",
    "what": "Animais"
  },
  {
    "name": "Cobra Coral",
    "url": "https://raw.githubusercontent.com/TioMarkZ/apis/main/animais/cobra_coral.jpg",
    "what": "Animais"
  },
  {
    "name": "cobra do milho",
    "url": "https://raw.githubusercontent.com/TioMarkZ/apis/main/animais/serpente_do_milho.jpg",
    "what": "Animais"
  },
  {
    "name": "Tigre Siberiano",
    "url": "https://raw.githubusercontent.com/TioMarkZ/apis/main/animais/tigre_siberiano.jpg",
    "what": "Animais"
  },
  {
    "name": "Tigre Branco",
    "url": "https://raw.githubusercontent.com/TioMarkZ/apis/main/animais/tigre_branco.jpg",
    "what": "Animais"
  },
  {
    "name": "Porquinho da Índia",
    "url": "https://raw.githubusercontent.com/TioMarkZ/apis/main/animais/porquinho_da_india.jpg",
    "what": "Animais"
  },
  {
    "name": "Porco espinho",
    "url": "https://raw.githubusercontent.com/TioMarkZ/apis/main/animais/porco_espinho.jpg",
    "what": "Animais"
  },
  {
    "name": "Porco",
    "url": "https://raw.githubusercontent.com/TioMarkZ/apis/main/animais/Porco.jpg",
    "what": "Animais"
  },
  {
    "name": "porco-formigueiro",
    "url": "https://raw.githubusercontent.com/TioMarkZ/apis/main/animais/porco-formigueiro.jpg",
    "what": "Animais"
  },
  {
    "name": "Orangotango",
    "url": "https://raw.githubusercontent.com/TioMarkZ/apis/main/animais/orangotango.jpg",
    "what": "Animais"
  },
  {
    "name": "Panda",
    "url": "https://raw.githubusercontent.com/TioMarkZ/apis/main/animais/panda.jpg",
    "what": "Animais"
  },
  {
    "name": "Panda Vermelho",
    "url": "https://raw.githubusercontent.com/TioMarkZ/apis/main/animais/panda_vermelho.jpg",
    "what": "Animais"
  },
  {
    "name": "Aranha",
    "url": "https://raw.githubusercontent.com/TioMarkZ/apis/main/animais/aranha.jpg",
    "what": "Animais"
  },
  {
    "name": "Aranha Saltadora",
    "url": "https://raw.githubusercontent.com/TioMarkZ/apis/main/animais/aranha_saltadora.jpg",
    "what": "Animais"
  },
  {
    "name": "Aranha Caranguejeira",
    "url": "https://raw.githubusercontent.com/TioMarkZ/apis/main/animais/aranha_caranguejeira.jpg",
    "what": "Animais"
  },
  {
    "name": "Macaco-aranha",
    "url": "https://raw.githubusercontent.com/TioMarkZ/apis/main/animais/macaco-aranha.jpg",
    "what": "Animais"
  },
  {
    "name": "Rinoceronte",
    "url": "https://raw.githubusercontent.com/TioMarkZ/apis/main/animais/rinoceronte.jpg",
    "what": "Animais"
  },
  {
    "name": "Hiena",
    "url": "https://raw.githubusercontent.com/TioMarkZ/apis/main/animais/hiena.jpg",
    "what": "Animais"
  },
  {
    "name": "Lhama",
    "url": "https://raw.githubusercontent.com/TioMarkZ/apis/main/animais/lhama.jpg",
    "what": "Animais"
  },
  {
    "name": "besouro rinoceronte",
    "url": "https://raw.githubusercontent.com/TioMarkZ/apis/main/animais/escaravelho_rinoceronte.jpg",
    "what": "Animais"
  },
  {
    "name": "Polvo",
    "url": "https://raw.githubusercontent.com/TioMarkZ/apis/main/animais/polvo.jpg",
    "what": "Animais"
  },
  {
    "name": "Golfinho",
    "url": "https://raw.githubusercontent.com/TioMarkZ/apis/main/animais/golfinho.jpg",
    "what": "Animais"
  },
  {
    "name": "Abutre",
    "url": "https://raw.githubusercontent.com/TioMarkZ/apis/main/animais/abutre.jpg",
    "what": "Animais"
  },
  {
    "name": "Canguru",
    "url": "https://raw.githubusercontent.com/TioMarkZ/apis/main/animais/canguru.jpg",
    "what": "Animais"
  },
  {
    "name": "Coala",
    "url": "https://raw.githubusercontent.com/TioMarkZ/apis/main/animais/coala.jpg",
    "what": "Animais"
  },
  {
    "name": "Avestruz",
    "url": "https://raw.githubusercontent.com/TioMarkZ/apis/main/animais/avestruz.jpg",
    "what": "Animais"
  },
  {
    "name": "Chimpanzé",
    "url": "https://raw.githubusercontent.com/TioMarkZ/apis/main/animais/chimpanze.jpg",
    "what": "Animais"
  },
  {
    "name": "Foca",
    "url": "https://raw.githubusercontent.com/TioMarkZ/apis/main/animais/foca.jpg",
    "what": "Animais"
  },
  {
    "name": "Orca",
    "url": "https://raw.githubusercontent.com/TioMarkZ/apis/main/animais/orca.jpg",
    "what": "Animais"
  },
  {
    "name": "Esquilo",
    "url": "https://raw.githubusercontent.com/TioMarkZ/apis/main/animais/esquilo.jpg",
    "what": "Animais"
  },
  {
    "name": "Esquilo-voador",
    "url": "https://raw.githubusercontent.com/TioMarkZ/apis/main/animais/esquilo_voador.jpg",
    "what": "Animais"
  },
  {
    "name": "esquilo-vermelho",
    "url": "https://raw.githubusercontent.com/TioMarkZ/apis/main/animais/esquilo-vermelho.jpg",
    "what": "Animais"
  },
  {
    "name": "Lontra",
    "url": "https://raw.githubusercontent.com/TioMarkZ/apis/main/animais/lontra.jpg",
    "what": "Animais"
  },
  {
    "name": "Lontra-europeia",
    "url": "https://raw.githubusercontent.com/TioMarkZ/apis/main/animais/lontra_europeia.jpg",
    "what": "Animais"
  },
  {
    "name": "Papagaio",
    "url": "https://raw.githubusercontent.com/TioMarkZ/apis/main/animais/papagaio.jpg",
    "what": "Animais"
  },
  {
    "name": "Papagaio do mar",
    "url": "https://raw.githubusercontent.com/TioMarkZ/apis/main/animais/papagaio-do-mar.jpg",
    "what": "Animais"
  },
  {
    "name": "Arara",
    "url": "https://raw.githubusercontent.com/TioMarkZ/apis/main/animais/arara.jpg",
    "what": "Animais"
  },
  {
    "name": "Arara azul",
    "url": "https://raw.githubusercontent.com/TioMarkZ/apis/main/animais/arara_azul.jpg",
    "what": "Animais"
  },
  {
    "name": "Urubu",
    "url": "https://raw.githubusercontent.com/TioMarkZ/apis/main/animais/urubu.jpg",
    "what": "Animais"
  },
  {
    "name": "Cisne",
    "url": "https://raw.githubusercontent.com/TioMarkZ/apis/main/animais/cisne.jpg",
    "what": "Animais"
  },
  {
    "name": "Cisne Negro",
    "url": "https://raw.githubusercontent.com/TioMarkZ/apis/main/animais/cisne_negro.jpg",
    "what": "Animais"
  },
  {
    "name": "Cisne-trombeteiro",
    "url": "https://raw.githubusercontent.com/TioMarkZ/apis/main/animais/cisne_trombeteiro.jpg",
    "what": "Animais"
  },
  {
    "name": "Águia",
    "url": "https://raw.githubusercontent.com/TioMarkZ/apis/main/animais/aguia.jpg",
    "what": "Animais"
  },
  {
    "name": "Águia dourada",
    "url": "https://raw.githubusercontent.com/TioMarkZ/apis/main/animais/aguia_dourada.jpg",
    "what": "Animais"
  },
  {
    "name": "Águia-pescadora",
    "url": "https://raw.githubusercontent.com/TioMarkZ/apis/main/animais/aguia_pescadora.jpg",
    "what": "Animais"
  },
  {
    "name": "Peixe",
    "url": "https://raw.githubusercontent.com/TioMarkZ/apis/main/animais/peixe.jpg",
    "what": "Animais"
  },
  {
    "name": "Peixe-palhaço",
    "url": "https://raw.githubusercontent.com/TioMarkZ/apis/main/animais/peixe_palhaco.jpg",
    "what": "Animais"
  },
  {
    "name": "Peixe-boi",
    "url": "https://raw.githubusercontent.com/TioMarkZ/apis/main/animais/peixe_boi.jpg",
    "what": "Animais"
  },
  {
    "name": "Peixe-lua",
    "url": "https://raw.githubusercontent.com/TioMarkZ/apis/main/animais/peixe_lua.jpg",
    "what": "Animais"
  },
  {
    "name": "Baiacu",
    "url": "https://raw.githubusercontent.com/TioMarkZ/apis/main/animais/peixe_baiacu.jpg",
    "what": "Animais"
  },
  {
    "name": "Lagarto",
    "url": "https://raw.githubusercontent.com/TioMarkZ/apis/main/animais/lagarto.jpg",
    "what": "Animais"
  },
  {
    "name": "Lagartixa",
    "url": "https://raw.githubusercontent.com/TioMarkZ/apis/main/animais/lagartixa.jpg",
    "what": "Animais"
  },
  {
    "name": "Hamster",
    "url": "https://raw.githubusercontent.com/TioMarkZ/apis/main/animais/hamster.jpg",
    "what": "Animais"
  },
  {
    "name": "Rato",
    "url": "https://raw.githubusercontent.com/TioMarkZ/apis/main/animais/rato.jpg",
    "what": "Animais"
  },
  {
    "name": "Rato do mato",
    "url": "https://raw.githubusercontent.com/TioMarkZ/apis/main/animais/rato_do_mato.jpg",
    "what": "Animais"
  },
  {
    "name": "Gafanhoto",
    "url": "https://raw.githubusercontent.com/TioMarkZ/apis/main/animais/gafanhoto.jpg",
    "what": "Animais"
  },
  {
    "name": "Caracol",
    "url": "https://raw.githubusercontent.com/TioMarkZ/apis/main/animais/caracol.jpg",
    "what": "Animais"
  },
  {
    "name": "Caracol-cone",
    "url": "https://raw.githubusercontent.com/TioMarkZ/apis/main/animais/caracol_cone.jpg",
    "what": "Animais"
  },
  {
    "name": "Tarântula",
    "url": "https://raw.githubusercontent.com/TioMarkZ/apis/main/animais/tarantula.jpg",
    "what": "Animais"
  },
  {
    "name": "Piranha",
    "url": "https://raw.githubusercontent.com/TioMarkZ/apis/main/animais/piranha.jpg",
    "what": "Animais"
  },
  {
    "name": "Morcego",
    "url": "https://raw.githubusercontent.com/TioMarkZ/apis/main/animais/morcego.jpg",
    "what": "Animais"
  },
  {
    "name": "Toupeira",
    "url": "https://raw.githubusercontent.com/TioMarkZ/apis/main/animais/toupeira.jpg",
    "what": "Animais"
  },
  {
    "name": "Pomba",
    "url": "https://raw.githubusercontent.com/TioMarkZ/apis/main/animais/pomba.jpg",
    "what": "Animais"
  },
  {
    "name": "Pombo",
    "url": "https://raw.githubusercontent.com/TioMarkZ/apis/main/animais/pombo.jpg",
    "what": "Animais"
  },
  {
    "name": "Raposa",
    "url": "https://raw.githubusercontent.com/TioMarkZ/apis/main/animais/raposa.jpg",
    "what": "Animais"
  },
  {
    "name": "Raposa branca",
    "url": "https://raw.githubusercontent.com/TioMarkZ/apis/main/animais/raposa_branca.jpg",
    "what": "Animais"
  },
  {
    "name": "Doninha",
    "url": "https://raw.githubusercontent.com/TioMarkZ/apis/main/animais/doninha.jpg",
    "what": "Animais"
  },
  {
    "name": "Doninha branca",
    "url": "https://raw.githubusercontent.com/TioMarkZ/apis/main/animais/doninha_branca.jpg",
    "what": "Animais"
  },
  {
    "name": "Texugo",
    "url": "https://raw.githubusercontent.com/TioMarkZ/apis/main/animais/texugo.jpg",
    "what": "Animais"
  },
  {
    "name": "Tamanduá",
    "url": "https://raw.githubusercontent.com/TioMarkZ/apis/main/animais/tamandua.jpg",
    "what": "Animais"
  },
  {
    "name": "Corvo",
    "url": "https://raw.githubusercontent.com/TioMarkZ/apis/main/animais/corvo.jpg",
    "what": "Animais"
  },
  {
    "name": "Alce",
    "url": "https://raw.githubusercontent.com/TioMarkZ/apis/main/animais/alce.jpg",
    "what": "Animais"
  },
  {
    "name": "Puma",
    "url": "https://raw.githubusercontent.com/TioMarkZ/apis/main/animais/puma.jpg",
    "what": "Animais"
  },
  {
    "name": "Pantera negra",
    "url": "https://raw.githubusercontent.com/TioMarkZ/apis/main/animais/pantera_negra.jpg",
    "what": "Animais"
  },
  {
    "name": "Foca Leoparda",
    "url": "https://raw.githubusercontent.com/TioMarkZ/apis/main/animais/foca_leoparda.jpg",
    "what": "Animais"
  },
  {
    "name": "Foca-anelada",
    "url": "https://raw.githubusercontent.com/TioMarkZ/apis/main/animais/foca_anelada.jpg",
    "what": "Animais"
  },
  {
    "name": "Dragão de komodo",
    "url": "https://raw.githubusercontent.com/TioMarkZ/apis/main/animais/dragao_de_komodo.jpg",
    "what": "Animais"
  },
  {
    "name": "Pangolim",
    "url": "https://raw.githubusercontent.com/TioMarkZ/apis/main/animais/pangolim.jpg",
    "what": "Animais"
  },
  {
    "name": "Ornitorrinco",
    "url": "https://raw.githubusercontent.com/TioMarkZ/apis/main/animais/ornitorrinco.jpg",
    "what": "Animais"
  },
  {
    "name": "kasuari closeup",
    "url": "https://raw.githubusercontent.com/TioMarkZ/apis/main/animais/kasuari_closeup.jpg",
    "what": "Animais"
  },
  {
    "name": "Suricata",
    "url": "https://raw.githubusercontent.com/TioMarkZ/apis/main/animais/suricata.jpg",
    "what": "Animais"
  },
  {
    "name": "Pelicano",
    "url": "https://raw.githubusercontent.com/TioMarkZ/apis/main/animais/pelicano.jpg",
    "what": "Animais"
  },
  {
    "name": "Capivara",
    "url": "https://raw.githubusercontent.com/TioMarkZ/apis/main/animais/capivara.jpg",
    "what": "Animais"
  },
  {
    "name": "Caranguejo",
    "url": "https://raw.githubusercontent.com/TioMarkZ/apis/main/animais/caranguejo.jpg",
    "what": "Animais"
  },
  {
    "name": "Lince",
    "url": "https://raw.githubusercontent.com/TioMarkZ/apis/main/animais/lince.jpg",
    "what": "Animais"
  },
  {
    "name": "Lince-canadense",
    "url": "https://raw.githubusercontent.com/TioMarkZ/apis/main/animais/lince_canadense.jpg",
    "what": "Animais"
  },
  {
    "name": "Guepardo",
    "url": "https://raw.githubusercontent.com/TioMarkZ/apis/main/animais/guepardo.jpg",
    "what": "Animais"
  },
  {
    "name": "Axolote",
    "url": "https://raw.githubusercontent.com/TioMarkZ/apis/main/animais/axolote.jpg",
    "what": "Animais"
  },
  {
    "name": "Pica-pau",
    "url": "https://raw.githubusercontent.com/TioMarkZ/apis/main/animais/pica_pau.jpg",
    "what": "Animais"
  },
  {
    "name": "Ouriço",
    "url": "https://raw.githubusercontent.com/TioMarkZ/apis/main/animais/ourico.jpg",
    "what": "Animais"
  },
  {
    "name": "Boto",
    "url": "https://raw.githubusercontent.com/TioMarkZ/apis/main/animais/boto.jpg",
    "what": "Animais"
  },
  {
    "name": "Coelho",
    "url": "https://raw.githubusercontent.com/TioMarkZ/apis/main/animais/coelho.jpg",
    "what": "Animais"
  },
  {
    "name": "Gavião real",
    "url": "https://raw.githubusercontent.com/TioMarkZ/apis/main/animais/gaviao_real.jpg",
    "what": "Animais"
  },
  {
    "name": "Carpa",
    "url": "https://raw.githubusercontent.com/TioMarkZ/apis/main/animais/carpa.jpg",
    "what": "Animais"
  },
  {
    "name": "Beija-flor",
    "url": "https://raw.githubusercontent.com/TioMarkZ/apis/main/animais/beija_flor.jpg",
    "what": "Animais"
  },
  {
    "name": "Besouro",
    "url": "https://raw.githubusercontent.com/TioMarkZ/apis/main/animais/besouro.jpg",
    "what": "Animais"
  },
  {
    "name": "Lagosta",
    "url": "https://raw.githubusercontent.com/TioMarkZ/apis/main/animais/lagosta.jpg",
    "what": "Animais"
  },
  {
    "name": "Gambá",
    "url": "https://raw.githubusercontent.com/TioMarkZ/apis/main/animais/gamba.jpg",
    "what": "Animais"
  },
  {
    "name": "Salamandra",
    "url": "https://raw.githubusercontent.com/TioMarkZ/apis/main/animais/salamandra.jpg",
    "what": "Animais"
  },
  {
    "name": "Mico leão dourado",
    "url": "https://raw.githubusercontent.com/TioMarkZ/apis/main/animais/mico_leao.jpg",
    "what": "Animais"
  },
  {
    "name": "Burro",
    "url": "https://raw.githubusercontent.com/TioMarkZ/apis/main/animais/burro.jpg",
    "what": "Animais"
  },
  {
    "name": "Jumenta",
    "url": "https://raw.githubusercontent.com/TioMarkZ/apis/main/animais/jumento.jpg",
    "what": "Animais"
  },
  {
    "name": "Preguiça",
    "url": "https://raw.githubusercontent.com/TioMarkZ/apis/main/animais/preguica.jpg",
    "what": "Animais"
  },
  {
    "name": "Javali",
    "url": "https://raw.githubusercontent.com/TioMarkZ/apis/main/animais/javali.jpg",
    "what": "Animais"
  },
  {
    "name": "Bode",
    "url": "https://raw.githubusercontent.com/TioMarkZ/apis/main/animais/bode.jpg",
    "what": "Animais"
  },
  {
    "name": "Galinha",
    "url": "https://raw.githubusercontent.com/TioMarkZ/apis/main/animais/galinha.jpg",
    "what": "Animais"
  },
  {
    "name": "Bisão",
    "url": "https://raw.githubusercontent.com/TioMarkZ/apis/main/animais/bisao.jpg",
    "what": "Animais"
  },
  {
    "name": "Carneiro",
    "url": "https://raw.githubusercontent.com/TioMarkZ/apis/main/animais/carneiro.jpg",
    "what": "Animais"
  },
  {
    "name": "Búfalo",
    "url": "https://raw.githubusercontent.com/TioMarkZ/apis/main/animais/bufalo.jpg",
    "what": "Animais"
  },
  {
    "name": "Vaca",
    "url": "https://raw.githubusercontent.com/TioMarkZ/apis/main/animais/vaca.jpg",
    "what": "Animais"
  },
  {
    "name": "Touro",
    "url": "https://raw.githubusercontent.com/TioMarkZ/apis/main/animais/touro.jpg",
    "what": "Animais"
  },
  {
    "name": "Cervo",
    "url": "https://raw.githubusercontent.com/TioMarkZ/apis/main/animais/cervo.jpg",
    "what": "Animais"
  },
  {
    "name": "Pavão",
    "url": "https://raw.githubusercontent.com/TioMarkZ/apis/main/animais/pavao.jpg",
    "what": "Animais"
  },
  {
    "name": "Escorpião",
    "url": "https://raw.githubusercontent.com/TioMarkZ/apis/main/animais/escorpiao.jpg",
    "what": "Animais"
  },
  {
    "name": "Pandinus imperator",
    "url": "https://raw.githubusercontent.com/TioMarkZ/apis/main/animais/escorpiao_imperador.jpg",
    "what": "Animais"
  },
  {
    "name": "Gato-do-mato",
    "url": "https://raw.githubusercontent.com/TioMarkZ/apis/main/animais/gato_do_mato.jpg",
    "what": "Animais"
  },
  {
    "name": "Floppa",
    "url": "https://raw.githubusercontent.com/TioMarkZ/apis/main/animais/floppa.jpg",
    "what": "Animais"
  },
  {
    "name": "Alpaca",
    "url": "https://raw.githubusercontent.com/TioMarkZ/apis/main/animais/alpaca.jpg",
    "what": "Animais"
  },
  {
    "name": "Guaxinim",
    "url": "https://raw.githubusercontent.com/TioMarkZ/apis/main/animais/guaxinim.jpg",
    "what": "Animais"
  },
  {
    "name": "Golfinho nariz de garrafa",
    "url": "https://raw.githubusercontent.com/TioMarkZ/apis/main/animais/golfinho_nariz_de_garrafa.jpg",
    "what": "Animais"
  },
  {
    "name": "Urso polar",
    "url": "https://raw.githubusercontent.com/TioMarkZ/apis/main/animais/urso_polar.jpg",
    "what": "Animais"
  },
  {
    "name": "Tucano de bico arco íris",
    "url": "https://raw.githubusercontent.com/TioMarkZ/apis/main/animais/tucano_de_bico_arco_iris.jpg",
    "what": "Animais"
  },
  {
    "name": "Quokka",
    "url": "https://raw.githubusercontent.com/TioMarkZ/apis/main/animais/quokka.jpg",
    "what": "Animais"
  },
  {
    "name": "Anta",
    "url": "https://raw.githubusercontent.com/TioMarkZ/apis/main/animais/anta.jpg",
    "what": "Animais"
  },
  {
    "name": "Iguana",
    "url": "https://raw.githubusercontent.com/TioMarkZ/apis/main/animais/iguana.jpg",
    "what": "Animais"
  },
  {
    "name": "Faisão-dourado",
    "url": "https://raw.githubusercontent.com/TioMarkZ/apis/main/animais/faisao_dourado.jpg",
    "what": "Animais"
  },
  {
    "name": "Tartaruga",
    "url": "https://raw.githubusercontent.com/TioMarkZ/apis/main/animais/tartaruga.jpg",
    "what": "Animais"
  },
  {
    "name": "Jabuti",
    "url": "https://raw.githubusercontent.com/TioMarkZ/apis/main/animais/jabuti.jpg",
    "what": "Animais"
  },
  {
    "name": "Tartaruga legítima",
    "url": "https://raw.githubusercontent.com/TioMarkZ/apis/main/animais/tartaruga_de_pente.jpg",
    "what": "Animais"
  },
  {
    "name": "Tartaruga-das-galápagos",
    "url": "https://raw.githubusercontent.com/TioMarkZ/apis/main/animais/tartaruga_das_galapagos.jpg",
    "what": "Animais"
  },
  {
    "name": "Tatu-bola",
    "url": "https://raw.githubusercontent.com/TioMarkZ/apis/main/animais/tatu_bola.jpg",
    "what": "Animais"
  },
  {
    "name": "Tatu",
    "url": "https://raw.githubusercontent.com/TioMarkZ/apis/main/animais/tatu.jpg",
    "what": "Animais"
  },
  {
    "name": "Quati",
    "url": "https://raw.githubusercontent.com/TioMarkZ/apis/main/animais/quati.jpg",
    "what": "Animais"
  },
  {
    "name": "Jaguatirica",
    "url": "https://raw.githubusercontent.com/TioMarkZ/apis/main/animais/jaguatirica.jpg",
    "what": "Animais"
  },
  {
    "name": "Ostra",
    "url": "https://raw.githubusercontent.com/TioMarkZ/apis/main/animais/ostra.jpg",
    "what": "Animais"
  },
  {
    "name": "Lêmure",
    "url": "https://raw.githubusercontent.com/TioMarkZ/apis/main/animais/lemure.jpg",
    "what": "Animais"
  },
  {
    "name": "Ariranha",
    "url": "https://raw.githubusercontent.com/TioMarkZ/apis/main/animais/ariranha.jpg",
    "what": "Animais"
  },
  {
    "name": "Garoupa",
    "url": "https://raw.githubusercontent.com/TioMarkZ/apis/main/animais/garoupa.jpg",
    "what": "Animais"
  },
  {
    "name": "Víbora de Chifres",
    "url": "https://raw.githubusercontent.com/TioMarkZ/apis/main/animais/vibora_de_chifres.jpg",
    "what": "Animais"
  },
  {
    "name": "Formiga",
    "url": "https://raw.githubusercontent.com/TioMarkZ/apis/main/animais/formiga.jpg",
    "what": "Animais"
  },
  {
    "name": "Diabo da tasmânia",
    "url": "https://raw.githubusercontent.com/TioMarkZ/apis/main/animais/diabo_da_tasmania.jpg",
    "what": "Animais"
  },
  {
    "name": "Mosca",
    "url": "https://raw.githubusercontent.com/TioMarkZ/apis/main/animais/mosca.jpg",
    "what": "Animais"
  },
  {
    "name": "Cutia",
    "url": "https://raw.githubusercontent.com/TioMarkZ/apis/main/animais/cutia.jpg",
    "what": "Animais"
  },
  {
    "name": "Sapo",
    "url": "https://raw.githubusercontent.com/TioMarkZ/apis/main/animais/sapo.jpg",
    "what": "Animais"
  },
  {
    "name": "Sapo cururu",
    "url": "https://raw.githubusercontent.com/TioMarkZ/apis/main/animais/sapo_cururu.jpg",
    "what": "Animais"
  },
  {
    "name": "Sapo verde",
    "url": "https://raw.githubusercontent.com/TioMarkZ/apis/main/animais/sapo_verde.jpg",
    "what": "Animais"
  },
  {
    "name": "Rã touro",
    "url": "https://raw.githubusercontent.com/TioMarkZ/apis/main/animais/sapo_touro.jpg",
    "what": "Animais"
  },
  {
    "name": "Morsa",
    "url": "https://raw.githubusercontent.com/TioMarkZ/apis/main/animais/morsa.jpg",
    "what": "Animais"
  },
  {
    "name": "Mosquito",
    "url": "https://raw.githubusercontent.com/TioMarkZ/apis/main/animais/mosquito.jpg",
    "what": "Animais"
  },
  {
    "name": "Cardeal",
    "url": "https://raw.githubusercontent.com/TioMarkZ/apis/main/animais/cardeal.jpg",
    "what": "Animais"
  },
  {
    "name": "Leão-marinho",
    "url": "https://raw.githubusercontent.com/TioMarkZ/apis/main/animais/leao_marinho.jpg",
    "what": "Animais"
  },
  {
    "name": "Barata",
    "url": "https://raw.githubusercontent.com/TioMarkZ/apis/main/animais/barata.jpg",
    "what": "Animais"
  },
  {
    "name": "Flamingo",
    "url": "https://raw.githubusercontent.com/TioMarkZ/apis/main/animais/flamingo.jpg",
    "what": "Animais"
  },
  {
    "name": "Abelha",
    "url": "https://raw.githubusercontent.com/TioMarkZ/apis/main/animais/abelha.jpg",
    "what": "Animais"
  },
  {
    "name": "Borboleta",
    "url": "https://raw.githubusercontent.com/TioMarkZ/apis/main/animais/borboleta.jpg",
    "what": "Animais"
  },
  {
    "name": "Cão-da-pradaria",
    "url": "https://raw.githubusercontent.com/TioMarkZ/apis/main/animais/cao_da_pradaria.jpg",
    "what": "Animais"
  },
  {
    "name": "Saíra-lagarta",
    "url": "https://raw.githubusercontent.com/TioMarkZ/apis/main/animais/saira_lagarta.jpg",
    "what": "Animais"
  },
  {
    "name": "Saíra-sapucaia",
    "url": "https://raw.githubusercontent.com/TioMarkZ/apis/main/animais/saira_sapucaia.jpg",
    "what": "Animais"
  },
  {
    "name": "Saíra-amarela",
    "url": "https://raw.githubusercontent.com/TioMarkZ/apis/main/animais/saira_amarela.jpg",
    "what": "Animais"
  },
  {
    "name": "Tangara",
    "url": "https://raw.githubusercontent.com/TioMarkZ/apis/main/animais/tangara.jpg",
    "what": "Animais"
  },
  {
    "name": "Chita",
    "url": "https://raw.githubusercontent.com/TioMarkZ/apis/main/animais/chita.jpg",
    "what": "Animais"
  },
  {
    "name": "Musaranho-elefante",
    "url": "https://raw.githubusercontent.com/TioMarkZ/apis/main/animais/musaranho_elefante.jpg",
    "what": "Animais"
  },
  {
    "name": "Saiga",
    "url": "https://raw.githubusercontent.com/TioMarkZ/apis/main/animais/antilope_saiga.jpg",
    "what": "Animais"
  },
  {
    "name": "Antílope-negro",
    "url": "https://raw.githubusercontent.com/TioMarkZ/apis/main/animais/antilope_negro.jpg",
    "what": "Animais"
  },
  {
    "name": "Dálmata",
    "url": "https://raw.githubusercontent.com/TioMarkZ/apis/main/animais/dalmata_domestico.jpg",
    "what": "Animais"
  },
  {
    "name": "Garça",
    "url": "https://raw.githubusercontent.com/TioMarkZ/apis/main/animais/garca.jpg",
    "what": "Animais"
  },
  {
    "name": "Pardal",
    "url": "https://raw.githubusercontent.com/TioMarkZ/apis/main/animais/pardal.jpg",
    "what": "Animais"
  },
  {
    "name": "Tucano",
    "url": "https://raw.githubusercontent.com/TioMarkZ/apis/main/animais/tucano.jpg",
    "what": "Animais"
  },
  {
    "name": "Libélula",
    "url": "https://raw.githubusercontent.com/TioMarkZ/apis/main/animais/libelula_comum.jpg",
    "what": "Animais"
  },
  {
    "name": "Husky Siberiano",
    "url": "https://raw.githubusercontent.com/TioMarkZ/apis/main/animais/husky_siberiano.jpg",
    "what": "Animais"
  },
  {
    "name": "Ganso",
    "url": "https://raw.githubusercontent.com/TioMarkZ/apis/main/animais/ganso.jpg",
    "what": "Animais"
  },
  {
    "name": "Lebre",
    "url": "https://raw.githubusercontent.com/TioMarkZ/apis/main/animais/lebre.jpg",
    "what": "Animais"
  }
]